vector_vault-7.4.9.8.data/data/LICENSE
vectorvault/__init__.py
vectorvault/ai.py
vectorvault/cloud_api.py
vectorvault/cloudmanager.py
vectorvault/credentials_manager.py
vectorvault/itemize.py
vectorvault/utils.py
vectorvault/vault.py
vector_vault-7.4.9.8.dist-info/LICENSE
vector_vault-7.4.9.8.dist-info/METADATA
vector_vault-7.4.9.8.dist-info/WHEEL
vector_vault-7.4.9.8.dist-info/top_level.txt
vector_vault-7.4.9.8.dist-info/RECORD
