Metadata-Version: 2.1
Name: vector-vault
Version: 7.4.9.8
Summary: Quickly create RAG apps, Agents, and Unleash the full power of AI with Vector Vault
Home-page: https://github.com/John-Rood/VectorVault
Author: VectorVault.io
Author-email: john@johnrood.com
Classifier: License :: Other/Proprietary License
Classifier: Programming Language :: Python
Classifier: Programming Language :: Python :: 3
Classifier: Programming Language :: Python :: 3.6
Classifier: Programming Language :: Python :: 3.7
Classifier: Programming Language :: Python :: 3.8
Classifier: Programming Language :: Python :: 3.9
License-File: LICENSE
Requires-Dist: numpy
Requires-Dist: requests
Requires-Dist: bs4
Requires-Dist: google-cloud-storage
Requires-Dist: annoy
Requires-Dist: openai
Requires-Dist: tiktoken
Requires-Dist: anthropic
Requires-Dist: pymupdf
Requires-Dist: google-genai
